pyplaywright/__init__.py
pyplaywright/websocket/__init__.py
pyplaywright/websocket/tracer/__init__.py
pyplaywright/websocket/tracer/tracer.py
pyplaywright-0.0.2.dist-info/LICENSE
pyplaywright-0.0.2.dist-info/METADATA
pyplaywright-0.0.2.dist-info/WHEEL
pyplaywright-0.0.2.dist-info/top_level.txt
pyplaywright-0.0.2.dist-info/RECORD
