Metadata-Version: 2.1
Name: pyplaywright
Version: 0.0.2
Summary: Python Playwright Utilities.
Author: Satyam Sinha
License-File: LICENSE
